wtforms_alchemy/__init__.py
wtforms_alchemy/exc.py
wtforms_alchemy/fields.py
wtforms_alchemy/generator.py
wtforms_alchemy/utils.py
wtforms_alchemy/validators.py
WTForms_Alchemy-0.19.0.dist-info/LICENSE
WTForms_Alchemy-0.19.0.dist-info/METADATA
WTForms_Alchemy-0.19.0.dist-info/WHEEL
WTForms_Alchemy-0.19.0.dist-info/top_level.txt
WTForms_Alchemy-0.19.0.dist-info/RECORD
