Metadata-Version: 2.1
Name: WTForms-Alchemy
Version: 0.19.0
Summary: Generates WTForms forms from SQLAlchemy models.
Home-page: https://github.com/kvesteri/wtforms-alchemy
Author: Konsta Vesterinen
Author-email: konsta@fastmonkeys.com
License: BSD
Platform: any
Classifier: Environment :: Web Environment
Classifier: Intended Audience :: Developers
Classifier: License :: OSI Approved :: BSD License
Classifier: Operating System :: OS Independent
Classifier: Programming Language :: Python
Classifier: Programming Language :: Python :: 3
Classifier: Programming Language :: Python :: 3.9
Classifier: Programming Language :: Python :: 3.10
Classifier: Programming Language :: Python :: 3.11
Classifier: Programming Language :: Python :: 3.12
Classifier: Programming Language :: Python :: 3.13
Classifier: Topic :: Internet :: WWW/HTTP :: Dynamic Content
Classifier: Topic :: Software Development :: Libraries :: Python Modules
License-File: LICENSE
Requires-Dist: SQLAlchemy>=1.4
Requires-Dist: WTForms>=3.1.0
Requires-Dist: WTForms-Components>=0.11.0
Requires-Dist: SQLAlchemy-Utils>=0.40.0
Provides-Extra: test
Requires-Dist: enum34; extra == "test"
Requires-Dist: pytest>=2.3; extra == "test"
Requires-Dist: Pygments>=1.2; extra == "test"
Requires-Dist: Jinja2>=2.3; extra == "test"
Requires-Dist: docutils>=0.10; extra == "test"
Requires-Dist: flexmock>=0.9.7; extra == "test"
Requires-Dist: ruff==0.7.4; extra == "test"
Requires-Dist: WTForms-Test>=0.1.1; extra == "test"
Requires-Dist: Babel>=1.3; extra == "test"
Requires-Dist: arrow>=0.3.4; extra == "test"
Requires-Dist: phonenumbers>=5.9.2; extra == "test"
Requires-Dist: intervals>=0.2.0; extra == "test"
Requires-Dist: passlib<2.0,>=1.6; extra == "test"
Requires-Dist: colour>=0.0.4; extra == "test"
Requires-Dist: SQLAlchemy-i18n>=0.8.2; extra == "test"
Requires-Dist: python-dateutil; extra == "test"
Provides-Extra: babel
Requires-Dist: Babel>=1.3; extra == "babel"
Provides-Extra: arrow
Requires-Dist: arrow>=0.3.4; extra == "arrow"
Provides-Extra: phone
Requires-Dist: phonenumbers>=5.9.2; extra == "phone"
Provides-Extra: intervals
Requires-Dist: intervals>=0.2.0; extra == "intervals"
Provides-Extra: password
Requires-Dist: passlib<2.0,>=1.6; extra == "password"
Provides-Extra: color
Requires-Dist: colour>=0.0.4; extra == "color"
Provides-Extra: i18n
Requires-Dist: SQLAlchemy-i18n>=0.8.2; extra == "i18n"
Provides-Extra: ipaddress
Provides-Extra: timezone
Requires-Dist: python-dateutil; extra == "timezone"
